{
    "origin_addresses": [
      "1600 Amphitheatre Pkwy, Mountain View, CA 94043, USA"
    ],
    "destination_addresses": [
      "New York, NY, USA",
      "Los Angeles, CA, USA",
      "Chicago, IL, USA"
    ],
    "rows": [
      {
        "elements": [
          {
            "status": "OK",
            "distance": {
              "text": "4,729 km",
              "value": 4729112
            },
            "duration": {
              "text": "1 day 19 hours",
              "value": 153673
            }
          },
          {
            "status": "OK",
            "distance": {
              "text": "568 km",
              "value": 567928
            },
            "duration": {
              "text": "5 hours 29 mins",
              "value": 19747
            }
          },
          {
            "status": "OK",
            "distance": {
              "text": "3,484 km",
              "value": 3483812
            },
            "duration": {
              "text": "1 day 7 hours",
              "value": 112023
            }
          }
        ]
      }
    ],
    "status": "OK"
  }